siriuspy/VERSION
siriuspy/__init__.py
siriuspy/callbacks.py
siriuspy/csdev.py
siriuspy/envars.py
siriuspy/thread.py
siriuspy/util.py
siriuspy/bsmp/__init__.py
siriuspy/bsmp/commands.py
siriuspy/bsmp/constants.py
siriuspy/bsmp/entities.py
siriuspy/bsmp/exceptions.py
siriuspy/bsmp/serial.py
siriuspy/bsmp/types.py
siriuspy/clientarch/__init__.py
siriuspy/clientarch/client.py
siriuspy/clientarch/devices.py
siriuspy/clientarch/exceptions.py
siriuspy/clientarch/pvarch.py
siriuspy/clientarch/time.py
siriuspy/clientconfigdb/__init__.py
siriuspy/clientconfigdb/_templates.py
siriuspy/clientconfigdb/configdb_client.py
siriuspy/clientconfigdb/configdb_document.py
siriuspy/clientconfigdb/pvsconfig.py
siriuspy/clientconfigdb/types/__init__.py
siriuspy/clientconfigdb/types/as_corrloop_params.py
siriuspy/clientconfigdb/types/as_diagnostics.py
siriuspy/clientconfigdb/types/as_pwrstate.py
siriuspy/clientconfigdb/types/as_rf.py
siriuspy/clientconfigdb/types/bo_chromcorr_params.py
siriuspy/clientconfigdb/types/bo_normalized.py
siriuspy/clientconfigdb/types/bo_orbcorr_respm.py
siriuspy/clientconfigdb/types/bo_orbit.py
siriuspy/clientconfigdb/types/bo_ramp.py
siriuspy/clientconfigdb/types/bo_tunecorr_params.py
siriuspy/clientconfigdb/types/global_config.py
siriuspy/clientconfigdb/types/si_bbadata.py
siriuspy/clientconfigdb/types/si_bbbproc.py
siriuspy/clientconfigdb/types/si_chromcorr_params.py
siriuspy/clientconfigdb/types/si_fastorbcorr_psconfig.py
siriuspy/clientconfigdb/types/si_fastorbcorr_respm.py
siriuspy/clientconfigdb/types/si_fofb.py
siriuspy/clientconfigdb/types/si_id.py
siriuspy/clientconfigdb/types/si_idff.py
siriuspy/clientconfigdb/types/si_orbcorr_respm.py
siriuspy/clientconfigdb/types/si_orbit.py
siriuspy/clientconfigdb/types/si_tunecorr_params.py
siriuspy/clientconfigdb/types/tb_normalized.py
siriuspy/clientconfigdb/types/tb_orbcorr_respm.py
siriuspy/clientconfigdb/types/tb_orbit.py
siriuspy/clientconfigdb/types/tb_posang_respm.py
siriuspy-2.99.0.dist-info/licenses/LICENSE
siriuspy-2.99.0.dist-info/METADATA
siriuspy-2.99.0.dist-info/WHEEL
siriuspy-2.99.0.dist-info/top_level.txt
siriuspy-2.99.0.dist-info/RECORD
