Metadata-Version: 2.4
Name: siriuspy
Version: 2.99.0
Summary: Development packages for Sirius
Home-page: https://github.com/lnls-sirius/dev-packages
Download-URL: https://github.com/lnls-sirius/dev-packages
Author: lnls-sirius
Maintainer-email: Ana Oliveira <ana.clara@lnls.br>, Ximenes Resende <xresende@gmail.com>, "Fernando H. de Sá" <fernandohds564@gmail.com>, Murilo Barbosa Alves <alvesb.murilo@gmail.com>
License-Expression: GPL-3.0
Project-URL: Homepage, https://github.com/lnls-sirius/dev-packages
Project-URL: Download, https://github.com/lnls-sirius/dev-packages
Project-URL: Repository, https://github.com/lnls-sirius/dev-packages.git
Project-URL: Issues, https://github.com/lnls-sirius/dev-packages/issues
Keywords: SIRIUS,python,EPICS
Classifier: Intended Audience :: Science/Research
Classifier: Programming Language :: Python
Classifier: Topic :: Scientific/Engineering
Requires-Python: >=3.6
License-File: LICENSE
Requires-Dist: aiohttp>=3.7.4
Requires-Dist: bottleneck>=1.3.2
Requires-Dist: mathphys
Requires-Dist: numpy<=1.23
Requires-Dist: scipy<=1.13
Requires-Dist: pyepics>=3.4.0
Requires-Dist: python-dateutil>=2.8.1
Requires-Dist: requests>=2.22.0
Requires-Dist: six>=1.13.0
Requires-Dist: pyyaml
Dynamic: download-url
Dynamic: home-page
Dynamic: license-file
Dynamic: requires-python
